Metadata-Version: 2.1
Name: Korotkiyserializer
Version: 0.1.1
Summary: some serialization
Home-page: UNKNOWN
Author: Korotkiy Pavel
Author-email: golden.essence.73@gmail.com
License: MIT
Platform: UNKNOWN
Classifier: Intended Audience :: Developers
Classifier: License :: OSI Approved :: MIT License
Classifier: Programming Language :: Python :: 3.10
Classifier: Operating System :: OS Independent
